{
  "name": "${project.name}",
  "version": "${project.version}",
  "description": "${project.description}",
  "platform": "complete",
  "dependencies": [
    {
      "name": "app-platform-complete",
      "version": "^VERSION",
      "preRelease": "false"
    }
  ],
  "modules": [
    {
      "name": "mod-organizations",
      "version": "^VERSION",
      "preRelease": "false"
    },
    {
      "name": "mod-organizations-storage",
      "version": "^VERSION",
      "preRelease": "false"
    },
    {
      "name": "mod-orders",
      "version": "^VERSION",
      "preRelease": "false"
    },
    {
      "name": "mod-orders-storage",
      "version": "^VERSION",
      "preRelease": "false"
    },
    {
      "name": "mod-invoice",
      "version": "^VERSION",
      "preRelease": "false"
    },
    {
      "name": "mod-invoice-storage",
      "version": "^VERSION",
      "preRelease": "false"
    },
    {
      "name": "mod-finance",
      "version": "^VERSION",
      "preRelease": "false"
    },
    {
      "name": "mod-finance-storage",
      "version": "^VERSION",
      "preRelease": "false"
    }
  ],
  "uiModules": [
    {
      "name": "folio_organizations",
      "version": "^VERSION",
      "preRelease": "false"
    },
    {
      "name": "folio_orders",
      "version": "^VERSION",
      "preRelease": "false"
    },
    {
      "name": "folio_invoice",
      "version": "^VERSION",
      "preRelease": "false"
    },
    {
      "name": "folio_finance",
      "version": "^VERSION",
      "preRelease": "false"
    },
    {
      "name": "folio_receiving",
      "version": "^VERSION",
      "preRelease": "false"
    },
    {
      "name": "folio_claims",
      "version": "^VERSION",
      "preRelease": "false"
    },
    {
      "name": "folio_acquisition-units",
      "version": "^VERSION",
      "preRelease": "false"
    },
    {
      "name": "folio_plugin-find-organization",
      "version": "^VERSION",
      "preRelease": "false"
    },
    {
      "name": "folio_plugin-find-contact",
      "version": "^VERSION",
      "preRelease": "false"
    },
    {
      "name": "folio_plugin-find-interface",
      "version": "^VERSION",
      "preRelease": "false"
    },
    {
      "name": "folio_plugin-find-fund",
      "version": "^VERSION",
      "preRelease": "false"
    },
    {
      "name": "folio_plugin-find-po-line",
      "version": "^VERSION",
      "preRelease": "false"
    }
  ]
}
